blue_gan/PyTorch_GAN.py
blue_gan/README.py
blue_gan/__init__.py
blue_gan/__main__.py
blue_gan/config.env
blue_gan/env.py
blue_gan/host.py
blue_gan/logger.py
blue_gan/stylegan2_pytorch.py
blue_gan/urls.py
blue_gan/.abcli/PyTorch_GAN.sh
blue_gan/.abcli/abcli.sh
blue_gan/.abcli/actions.sh
blue_gan/.abcli/aka.sh
blue_gan/.abcli/alias.sh
blue_gan/.abcli/blue_gan.sh
blue_gan/.abcli/browse.sh
blue_gan/.abcli/ingest.sh
blue_gan/.abcli/install.sh
blue_gan/.abcli/stylegan2_pytorch.sh
blue_gan/.abcli/tests/README.sh
blue_gan/.abcli/tests/help.sh
blue_gan/.abcli/tests/version.sh
blue_gan/help/PyTorch_GAN.py
blue_gan/help/__init__.py
blue_gan/help/__main__.py
blue_gan/help/functions.py
blue_gan/help/ingest.py
blue_gan/help/stylegan2_pytorch.py
blue_gan/ingest/__init__.py
blue_gan/ingest/__main__.py
blue_gan/ingest/animals10.py
blue_gan-4.47.1.dist-info/LICENSE
blue_gan-4.47.1.dist-info/METADATA
blue_gan-4.47.1.dist-info/WHEEL
blue_gan-4.47.1.dist-info/top_level.txt
blue_gan-4.47.1.dist-info/RECORD
