Metadata-Version: 2.2
Name: blue_gan
Version: 4.47.1
Summary: 🖌️ A command interface to GANs.
Home-page: https://github.com/kamangir/blue-gan
Author: Arash Abadpour (Kamangir)
Author-email: arash@kamangir.net
License: Public Domain
Classifier: Programming Language :: Python :: 3
Classifier: Programming Language :: Unix Shell
Classifier: License :: Public Domain
Classifier: Operating System :: OS Independent
License-File: LICENSE
Requires-Dist: abcli
Requires-Dist: stylegan2_pytorch
Dynamic: author
Dynamic: author-email
Dynamic: classifier
Dynamic: description
Dynamic: description-content-type
Dynamic: home-page
Dynamic: license
Dynamic: requires-dist
Dynamic: summary
